LICENSE
README.md
setup.py
hellocash/__init__.py
hellocash/articles.py
hellocash/cash_book.py
hellocash/client.py
hellocash/employees.py
hellocash/invoices.py
hellocash/payment_methods.py
hellocash/services.py
hellocash/users.py
hellocash.egg-info/PKG-INFO
hellocash.egg-info/SOURCES.txt
hellocash.egg-info/dependency_links.txt
hellocash.egg-info/requires.txt
hellocash.egg-info/top_level.txt