Metadata-Version: 2.1
Name: hellocash
Version: 0.2.0
Summary: Unofficial Python SDK for HelloCash API
Author: Paul Harrer
Author-email: mail@paulharrer.at
Project-URL: GitHub, https://github.com/PaulHarrer/hellocash-python
License-File: LICENSE
Requires-Dist: requests
